odoo/addons/maintenance_project_plan/README.rst
odoo/addons/maintenance_project_plan/__init__.py
odoo/addons/maintenance_project_plan/__manifest__.py
odoo/addons/maintenance_project_plan/data/demo_maintenance_project_plan.xml
odoo/addons/maintenance_project_plan/i18n/es.po
odoo/addons/maintenance_project_plan/i18n/it.po
odoo/addons/maintenance_project_plan/i18n/maintenance_project_plan.pot
odoo/addons/maintenance_project_plan/models/__init__.py
odoo/addons/maintenance_project_plan/models/maintenance_equipment.py
odoo/addons/maintenance_project_plan/models/maintenance_plan.py
odoo/addons/maintenance_project_plan/readme/CONTRIBUTORS.rst
odoo/addons/maintenance_project_plan/readme/DESCRIPTION.rst
odoo/addons/maintenance_project_plan/static/description/icon.png
odoo/addons/maintenance_project_plan/static/description/index.html
odoo/addons/maintenance_project_plan/tests/__init__.py
odoo/addons/maintenance_project_plan/tests/test_maintenance_project_plan.py
odoo/addons/maintenance_project_plan/views/maintenance_equipment_views.xml
odoo/addons/maintenance_project_plan/views/maintenance_plan_views.xml
odoo14_addon_maintenance_project_plan-14.0.1.0.1.dist-info/METADATA
odoo14_addon_maintenance_project_plan-14.0.1.0.1.dist-info/WHEEL
odoo14_addon_maintenance_project_plan-14.0.1.0.1.dist-info/top_level.txt
odoo14_addon_maintenance_project_plan-14.0.1.0.1.dist-info/RECORD
