Metadata-Version: 2.1
Name: odoo14-addon-maintenance-project-plan
Version: 14.0.1.0.1
Summary: Adds project and task to a Maintenance Plan
Home-page: https://github.com/OCA/maintenance
Author: Odoo Community Association (OCA), Solvos
Author-email: support@odoo-community.org
License: AGPL-3
Platform: UNKNOWN
Classifier: Programming Language :: Python
Classifier: Framework :: Odoo
Classifier: Framework :: Odoo :: 14.0
Classifier: License :: OSI Approved :: GNU Affero General Public License v3
Requires-Python: >=3.6
Requires-Dist: odoo14-addon-maintenance-plan
Requires-Dist: odoo14-addon-maintenance-project
Requires-Dist: odoo <14.1dev,>=14.0a
